rdfox/__init__.py
rdfox/evaluation_license.txt
rdfox/examples/C++/CppRDFoxDemo.cpp
rdfox/examples/C++/compile-shared-and-run.sh
rdfox/examples/C++/compile-static-and-run.sh
rdfox/examples/C/CRDFoxDemo.c
rdfox/examples/C/compile-shared-and-run.sh
rdfox/examples/C/compile-static-and-run.sh
rdfox/examples/Java/build.xml
rdfox/examples/Java/tech/oxfordsemantic/jrdfox/JRDFoxDemo.java
rdfox/examples/Java/tech/oxfordsemantic/jrdfox/data/additional-rules.txt
rdfox/examples/Java/tech/oxfordsemantic/jrdfox/data/lubm1-new.ttl
rdfox/examples/Java/tech/oxfordsemantic/jrdfox/data/lubm1.ttl
rdfox/examples/Java/tech/oxfordsemantic/jrdfox/data/univ-bench.owl
rdfox/examples/data/additional-rules.txt
rdfox/examples/data/lubm1-new.ttl
rdfox/examples/data/lubm1.ttl
rdfox/examples/data/univ-bench.owl
rdfox/include/CRDFox/CRDFox.h
rdfox/lib/JRDFox.jar
rdfox/lib/libRDFox-static.a
rdfox/lib/libRDFox.so
rdfox/readme.txt
rdfox/version.txt
rdfox/RDFox
rdfox/__main__.py
rdfox-7.1.1.dist-info/METADATA
rdfox-7.1.1.dist-info/WHEEL
rdfox-7.1.1.dist-info/entry_points.txt
rdfox-7.1.1.dist-info/RECORD
