Metadata-Version: 2.1
Name: rdfox
Version: 7.1.1
Summary:
Project-URL: Homepage, https://www.oxfordsemantic.tech/product
Project-URL: Source Code, https://github.com/ricklupton/rdfox-pypi
Project-URL: Bug Tracker, https://github.com/ricklupton/rdfox-pypi/issues
Requires-Python: ~=3.5
